{"BACKGROUND": {"0": 19537856, "0.1": 0, "0.5": 0, "1": 0, "1.5": 0, "2.0": 0, "2.5": 0, "3.0": 0, "4.0": 0, "5.0": 0, "7.5": 0, "10.0": 0, "12.5": 0, "15.0": 0, "20.0": 0}, "VEHICLE": {"0": 81649, "0.1": 18710, "0.5": 18, "1": 0, "1.5": 0, "2.0": 691, "2.5": 1128, "3.0": 1327, "4.0": 3462, "5.0": 8208, "7.5": 10234, "10.0": 3709, "12.5": 0, "15.0": 0, "20.0": 0}, "PEDESTRIAN": {"0": 7998, "0.1": 484, "0.5": 3162, "1": 28832, "1.5": 331, "2.0": 0, "2.5": 0, "3.0": 0, "4.0": 0, "5.0": 0, "7.5": 0, "10.0": 0, "12.5": 0, "15.0": 0, "20.0": 0}, "SIGN": {"0": 161309, "0.1": 4425, "0.5": 46, "1": 0, "1.5": 24, "2.0": 0, "2.5": 0, "3.0": 0, "4.0": 0, "5.0": 0, "7.5": 0, "10.0": 0, "12.5": 0, "15.0": 0, "20.0": 0}, "CYCLIST": {"0": 8171, "0.1": 7645, "0.5": 2054, "1": 843, "1.5": 0, "2.0": 0, "2.5": 0, "3.0": 0, "4.0": 0, "5.0": 0, "7.5": 0, "10.0": 0, "12.5": 0, "15.0": 0, "20.0": 0}}