{"BACKGROUND": {"0": 16909203, "0.1": 0, "0.5": 0, "1": 0, "1.5": 0, "2.0": 0, "2.5": 0, "3.0": 0, "4.0": 0, "5.0": 0, "7.5": 0, "10.0": 0, "12.5": 0, "15.0": 0, "20.0": 0}, "VEHICLE": {"0": 117882, "0.1": 43504, "0.5": 427, "1": 785, "1.5": 1298, "2.0": 685, "2.5": 629, "3.0": 264, "4.0": 18, "5.0": 0, "7.5": 108, "10.0": 0, "12.5": 11320, "15.0": 5909, "20.0": 0}, "PEDESTRIAN": {"0": 0, "0.1": 116, "0.5": 3509, "1": 9608, "1.5": 887, "2.0": 2259, "2.5": 48, "3.0": 474, "4.0": 12, "5.0": 1, "7.5": 0, "10.0": 0, "12.5": 0, "15.0": 0, "20.0": 0}, "SIGN": {"0": 44358, "0.1": 2484, "0.5": 44, "1": 0, "1.5": 0, "2.0": 0, "2.5": 0, "3.0": 0, "4.0": 0, "5.0": 0, "7.5": 0, "10.0": 0, "12.5": 0, "15.0": 0, "20.0": 0}, "CYCLIST": {"0": 0, "0.1": 0, "0.5": 0, "1": 0, "1.5": 0, "2.0": 0, "2.5": 0, "3.0": 25614, "4.0": 247, "5.0": 0, "7.5": 0, "10.0": 0, "12.5": 0, "15.0": 0, "20.0": 0}}