{"BACKGROUND": {"0": 10174997, "0.1": 0, "0.5": 0, "1": 0, "1.5": 0, "2.0": 0, "2.5": 0, "3.0": 0, "4.0": 0, "5.0": 0, "7.5": 0, "10.0": 0, "12.5": 0, "15.0": 0, "20.0": 0}, "ANIMAL": {"0": 0, "0.1": 0, "0.5": 0, "1": 0, "1.5": 0, "2.0": 0, "2.5": 0, "3.0": 0, "4.0": 0, "5.0": 0, "7.5": 0, "10.0": 0, "12.5": 0, "15.0": 0, "20.0": 0}, "ARTICULATED_BUS": {"0": 0, "0.1": 0, "0.5": 0, "1": 0, "1.5": 0, "2.0": 0, "2.5": 0, "3.0": 0, "4.0": 0, "5.0": 0, "7.5": 0, "10.0": 0, "12.5": 0, "15.0": 0, "20.0": 0}, "BICYCLE": {"0": 29, "0.1": 11, "0.5": 0, "1": 0, "1.5": 0, "2.0": 0, "2.5": 0, "3.0": 0, "4.0": 0, "5.0": 0, "7.5": 0, "10.0": 0, "12.5": 0, "15.0": 0, "20.0": 0}, "BICYCLIST": {"0": 1886, "0.1": 233, "0.5": 0, "1": 0, "1.5": 0, "2.0": 0, "2.5": 0, "3.0": 0, "4.0": 0, "5.0": 0, "7.5": 0, "10.0": 0, "12.5": 0, "15.0": 0, "20.0": 0}, "BOLLARD": {"0": 8640, "0.1": 0, "0.5": 0, "1": 0, "1.5": 0, "2.0": 0, "2.5": 0, "3.0": 0, "4.0": 0, "5.0": 0, "7.5": 0, "10.0": 0, "12.5": 0, "15.0": 0, "20.0": 0}, "BOX_TRUCK": {"0": 17520, "0.1": 8093, "0.5": 200, "1": 22, "1.5": 28, "2.0": 26, "2.5": 0, "3.0": 24, "4.0": 264, "5.0": 546, "7.5": 840, "10.0": 1012, "12.5": 0, "15.0": 0, "20.0": 0}, "BUS": {"0": 0, "0.1": 0, "0.5": 0, "1": 0, "1.5": 0, "2.0": 0, "2.5": 0, "3.0": 0, "4.0": 0, "5.0": 0, "7.5": 0, "10.0": 0, "12.5": 0, "15.0": 0, "20.0": 0}, "CONSTRUCTION_BARREL": {"0": 0, "0.1": 0, "0.5": 0, "1": 0, "1.5": 0, "2.0": 0, "2.5": 0, "3.0": 0, "4.0": 0, "5.0": 0, "7.5": 0, "10.0": 0, "12.5": 0, "15.0": 0, "20.0": 0}, "CONSTRUCTION_CONE": {"0": 0, "0.1": 0, "0.5": 0, "1": 0, "1.5": 0, "2.0": 0, "2.5": 0, "3.0": 0, "4.0": 0, "5.0": 0, "7.5": 0, "10.0": 0, "12.5": 0, "15.0": 0, "20.0": 0}, "DOG": {"0": 0, "0.1": 0, "0.5": 0, "1": 0, "1.5": 0, "2.0": 0, "2.5": 0, "3.0": 0, "4.0": 0, "5.0": 0, "7.5": 0, "10.0": 0, "12.5": 0, "15.0": 0, "20.0": 0}, "LARGE_VEHICLE": {"0": 4, "0.1": 348, "0.5": 269, "1": 172, "1.5": 349, "2.0": 485, "2.5": 0, "3.0": 0, "4.0": 0, "5.0": 0, "7.5": 0, "10.0": 0, "12.5": 0, "15.0": 0, "20.0": 0}, "MESSAGE_BOARD_TRAILER": {"0": 0, "0.1": 0, "0.5": 0, "1": 0, "1.5": 0, "2.0": 0, "2.5": 0, "3.0": 0, "4.0": 0, "5.0": 0, "7.5": 0, "10.0": 0, "12.5": 0, "15.0": 0, "20.0": 0}, "MOBILE_PEDESTRIAN_CROSSING_SIGN": {"0": 0, "0.1": 0, "0.5": 0, "1": 0, "1.5": 0, "2.0": 0, "2.5": 0, "3.0": 0, "4.0": 0, "5.0": 0, "7.5": 0, "10.0": 0, "12.5": 0, "15.0": 0, "20.0": 0}, "MOTORCYCLE": {"0": 0, "0.1": 0, "0.5": 0, "1": 0, "1.5": 0, "2.0": 0, "2.5": 0, "3.0": 0, "4.0": 0, "5.0": 0, "7.5": 0, "10.0": 0, "12.5": 0, "15.0": 0, "20.0": 0}, "MOTORCYCLIST": {"0": 0, "0.1": 0, "0.5": 0, "1": 0, "1.5": 0, "2.0": 0, "2.5": 0, "3.0": 0, "4.0": 0, "5.0": 0, "7.5": 0, "10.0": 0, "12.5": 0, "15.0": 0, "20.0": 0}, "OFFICIAL_SIGNALER": {"0": 0, "0.1": 0, "0.5": 0, "1": 0, "1.5": 0, "2.0": 0, "2.5": 0, "3.0": 0, "4.0": 0, "5.0": 0, "7.5": 0, "10.0": 0, "12.5": 0, "15.0": 0, "20.0": 0}, "PEDESTRIAN": {"0": 7102, "0.1": 2857, "0.5": 947, "1": 8285, "1.5": 196, "2.0": 0, "2.5": 0, "3.0": 13, "4.0": 0, "5.0": 0, "7.5": 0, "10.0": 0, "12.5": 0, "15.0": 0, "20.0": 0}, "RAILED_VEHICLE": {"0": 0, "0.1": 0, "0.5": 0, "1": 0, "1.5": 0, "2.0": 0, "2.5": 0, "3.0": 0, "4.0": 0, "5.0": 0, "7.5": 0, "10.0": 0, "12.5": 0, "15.0": 0, "20.0": 0}, "REGULAR_VEHICLE": {"0": 636226, "0.1": 196328, "0.5": 7872, "1": 16237, "1.5": 12271, "2.0": 44586, "2.5": 86526, "3.0": 112941, "4.0": 45561, "5.0": 79866, "7.5": 38152, "10.0": 117407, "12.5": 1397, "15.0": 77, "20.0": 0}, "SCHOOL_BUS": {"0": 0, "0.1": 0, "0.5": 0, "1": 0, "1.5": 0, "2.0": 0, "2.5": 0, "3.0": 0, "4.0": 0, "5.0": 0, "7.5": 0, "10.0": 0, "12.5": 0, "15.0": 0, "20.0": 0}, "SIGN": {"0": 0, "0.1": 0, "0.5": 0, "1": 0, "1.5": 0, "2.0": 0, "2.5": 0, "3.0": 0, "4.0": 0, "5.0": 0, "7.5": 0, "10.0": 0, "12.5": 0, "15.0": 0, "20.0": 0}, "STOP_SIGN": {"0": 43458, "0.1": 3557, "0.5": 2699, "1": 0, "1.5": 0, "2.0": 0, "2.5": 0, "3.0": 0, "4.0": 0, "5.0": 0, "7.5": 0, "10.0": 0, "12.5": 0, "15.0": 0, "20.0": 0}, "STROLLER": {"0": 0, "0.1": 0, "0.5": 0, "1": 0, "1.5": 0, "2.0": 0, "2.5": 0, "3.0": 0, "4.0": 0, "5.0": 0, "7.5": 0, "10.0": 0, "12.5": 0, "15.0": 0, "20.0": 0}, "TRAFFIC_LIGHT_TRAILER": {"0": 0, "0.1": 0, "0.5": 0, "1": 0, "1.5": 0, "2.0": 0, "2.5": 0, "3.0": 0, "4.0": 0, "5.0": 0, "7.5": 0, "10.0": 0, "12.5": 0, "15.0": 0, "20.0": 0}, "TRUCK": {"0": 0, "0.1": 0, "0.5": 0, "1": 0, "1.5": 0, "2.0": 0, "2.5": 0, "3.0": 0, "4.0": 0, "5.0": 0, "7.5": 0, "10.0": 0, "12.5": 0, "15.0": 0, "20.0": 0}, "TRUCK_CAB": {"0": 0, "0.1": 0, "0.5": 0, "1": 0, "1.5": 0, "2.0": 0, "2.5": 0, "3.0": 0, "4.0": 0, "5.0": 0, "7.5": 0, "10.0": 0, "12.5": 0, "15.0": 0, "20.0": 0}, "VEHICULAR_TRAILER": {"0": 0, "0.1": 0, "0.5": 0, "1": 0, "1.5": 0, "2.0": 0, "2.5": 0, "3.0": 0, "4.0": 0, "5.0": 0, "7.5": 0, "10.0": 0, "12.5": 0, "15.0": 0, "20.0": 0}, "WHEELCHAIR": {"0": 0, "0.1": 0, "0.5": 0, "1": 0, "1.5": 0, "2.0": 0, "2.5": 0, "3.0": 0, "4.0": 0, "5.0": 0, "7.5": 0, "10.0": 0, "12.5": 0, "15.0": 0, "20.0": 0}, "WHEELED_DEVICE": {"0": 0, "0.1": 0, "0.5": 0, "1": 0, "1.5": 0, "2.0": 0, "2.5": 0, "3.0": 0, "4.0": 0, "5.0": 0, "7.5": 0, "10.0": 0, "12.5": 0, "15.0": 0, "20.0": 0}, "WHEELED_RIDER": {"0": 0, "0.1": 0, "0.5": 0, "1": 0, "1.5": 0, "2.0": 0, "2.5": 0, "3.0": 0, "4.0": 0, "5.0": 0, "7.5": 0, "10.0": 0, "12.5": 0, "15.0": 0, "20.0": 0}}