{"BACKGROUND": {"0": 10738853, "0.1": 0, "0.5": 0, "1": 0, "1.5": 0, "2.0": 0, "2.5": 0, "3.0": 0, "4.0": 0, "5.0": 0, "7.5": 0, "10.0": 0, "12.5": 0, "15.0": 0, "20.0": 0}, "ANIMAL": {"0": 0, "0.1": 0, "0.5": 0, "1": 0, "1.5": 0, "2.0": 0, "2.5": 0, "3.0": 0, "4.0": 0, "5.0": 0, "7.5": 0, "10.0": 0, "12.5": 0, "15.0": 0, "20.0": 0}, "ARTICULATED_BUS": {"0": 0, "0.1": 0, "0.5": 0, "1": 0, "1.5": 0, "2.0": 0, "2.5": 0, "3.0": 0, "4.0": 0, "5.0": 0, "7.5": 0, "10.0": 0, "12.5": 0, "15.0": 0, "20.0": 0}, "BICYCLE": {"0": 2405, "0.1": 140, "0.5": 0, "1": 12, "1.5": 5, "2.0": 10, "2.5": 5, "3.0": 0, "4.0": 0, "5.0": 0, "7.5": 0, "10.0": 0, "12.5": 0, "15.0": 0, "20.0": 0}, "BICYCLIST": {"0": 0, "0.1": 0, "0.5": 4, "1": 120, "1.5": 152, "2.0": 605, "2.5": 2030, "3.0": 712, "4.0": 85, "5.0": 0, "7.5": 0, "10.0": 0, "12.5": 0, "15.0": 0, "20.0": 0}, "BOLLARD": {"0": 629, "0.1": 0, "0.5": 0, "1": 0, "1.5": 0, "2.0": 0, "2.5": 0, "3.0": 0, "4.0": 0, "5.0": 0, "7.5": 0, "10.0": 0, "12.5": 0, "15.0": 0, "20.0": 0}, "BOX_TRUCK": {"0": 0, "0.1": 0, "0.5": 8284, "1": 37453, "1.5": 87917, "2.0": 34054, "2.5": 443154, "3.0": 352730, "4.0": 133842, "5.0": 237578, "7.5": 0, "10.0": 0, "12.5": 0, "15.0": 0, "20.0": 0}, "BUS": {"0": 0, "0.1": 0, "0.5": 0, "1": 0, "1.5": 0, "2.0": 0, "2.5": 0, "3.0": 0, "4.0": 0, "5.0": 0, "7.5": 0, "10.0": 0, "12.5": 0, "15.0": 0, "20.0": 0}, "CONSTRUCTION_BARREL": {"0": 0, "0.1": 0, "0.5": 0, "1": 0, "1.5": 0, "2.0": 0, "2.5": 0, "3.0": 0, "4.0": 0, "5.0": 0, "7.5": 0, "10.0": 0, "12.5": 0, "15.0": 0, "20.0": 0}, "CONSTRUCTION_CONE": {"0": 160, "0.1": 0, "0.5": 0, "1": 0, "1.5": 0, "2.0": 0, "2.5": 0, "3.0": 0, "4.0": 0, "5.0": 0, "7.5": 0, "10.0": 0, "12.5": 0, "15.0": 0, "20.0": 0}, "DOG": {"0": 0, "0.1": 0, "0.5": 0, "1": 0, "1.5": 0, "2.0": 0, "2.5": 0, "3.0": 0, "4.0": 0, "5.0": 0, "7.5": 0, "10.0": 0, "12.5": 0, "15.0": 0, "20.0": 0}, "LARGE_VEHICLE": {"0": 0, "0.1": 0, "0.5": 0, "1": 0, "1.5": 0, "2.0": 0, "2.5": 0, "3.0": 0, "4.0": 0, "5.0": 0, "7.5": 0, "10.0": 0, "12.5": 0, "15.0": 0, "20.0": 0}, "MESSAGE_BOARD_TRAILER": {"0": 0, "0.1": 0, "0.5": 0, "1": 0, "1.5": 0, "2.0": 0, "2.5": 0, "3.0": 0, "4.0": 0, "5.0": 0, "7.5": 0, "10.0": 0, "12.5": 0, "15.0": 0, "20.0": 0}, "MOBILE_PEDESTRIAN_CROSSING_SIGN": {"0": 0, "0.1": 0, "0.5": 0, "1": 0, "1.5": 0, "2.0": 0, "2.5": 0, "3.0": 0, "4.0": 0, "5.0": 0, "7.5": 0, "10.0": 0, "12.5": 0, "15.0": 0, "20.0": 0}, "MOTORCYCLE": {"0": 0, "0.1": 0, "0.5": 0, "1": 0, "1.5": 0, "2.0": 0, "2.5": 0, "3.0": 0, "4.0": 0, "5.0": 0, "7.5": 0, "10.0": 0, "12.5": 0, "15.0": 0, "20.0": 0}, "MOTORCYCLIST": {"0": 0, "0.1": 0, "0.5": 0, "1": 0, "1.5": 0, "2.0": 0, "2.5": 0, "3.0": 0, "4.0": 0, "5.0": 0, "7.5": 0, "10.0": 0, "12.5": 0, "15.0": 0, "20.0": 0}, "OFFICIAL_SIGNALER": {"0": 0, "0.1": 0, "0.5": 0, "1": 0, "1.5": 0, "2.0": 0, "2.5": 0, "3.0": 0, "4.0": 0, "5.0": 0, "7.5": 0, "10.0": 0, "12.5": 0, "15.0": 0, "20.0": 0}, "PEDESTRIAN": {"0": 5831, "0.1": 305, "0.5": 2407, "1": 36367, "1.5": 1146, "2.0": 0, "2.5": 0, "3.0": 3, "4.0": 0, "5.0": 0, "7.5": 0, "10.0": 0, "12.5": 0, "15.0": 0, "20.0": 0}, "RAILED_VEHICLE": {"0": 0, "0.1": 0, "0.5": 0, "1": 0, "1.5": 0, "2.0": 0, "2.5": 0, "3.0": 0, "4.0": 0, "5.0": 0, "7.5": 0, "10.0": 0, "12.5": 0, "15.0": 0, "20.0": 0}, "REGULAR_VEHICLE": {"0": 1081845, "0.1": 184563, "0.5": 16408, "1": 12364, "1.5": 13641, "2.0": 12111, "2.5": 14284, "3.0": 85646, "4.0": 46287, "5.0": 20650, "7.5": 9823, "10.0": 0, "12.5": 0, "15.0": 0, "20.0": 0}, "SCHOOL_BUS": {"0": 0, "0.1": 0, "0.5": 0, "1": 0, "1.5": 0, "2.0": 0, "2.5": 0, "3.0": 0, "4.0": 0, "5.0": 0, "7.5": 0, "10.0": 0, "12.5": 0, "15.0": 0, "20.0": 0}, "SIGN": {"0": 7946, "0.1": 164, "0.5": 0, "1": 0, "1.5": 0, "2.0": 0, "2.5": 0, "3.0": 0, "4.0": 0, "5.0": 0, "7.5": 0, "10.0": 0, "12.5": 0, "15.0": 0, "20.0": 0}, "STOP_SIGN": {"0": 0, "0.1": 0, "0.5": 0, "1": 0, "1.5": 0, "2.0": 0, "2.5": 0, "3.0": 0, "4.0": 0, "5.0": 0, "7.5": 0, "10.0": 0, "12.5": 0, "15.0": 0, "20.0": 0}, "STROLLER": {"0": 0, "0.1": 0, "0.5": 0, "1": 0, "1.5": 0, "2.0": 0, "2.5": 0, "3.0": 0, "4.0": 0, "5.0": 0, "7.5": 0, "10.0": 0, "12.5": 0, "15.0": 0, "20.0": 0}, "TRAFFIC_LIGHT_TRAILER": {"0": 0, "0.1": 0, "0.5": 0, "1": 0, "1.5": 0, "2.0": 0, "2.5": 0, "3.0": 0, "4.0": 0, "5.0": 0, "7.5": 0, "10.0": 0, "12.5": 0, "15.0": 0, "20.0": 0}, "TRUCK": {"0": 3, "0.1": 0, "0.5": 0, "1": 0, "1.5": 0, "2.0": 0, "2.5": 0, "3.0": 0, "4.0": 0, "5.0": 0, "7.5": 8841, "10.0": 0, "12.5": 0, "15.0": 0, "20.0": 0}, "TRUCK_CAB": {"0": 0, "0.1": 0, "0.5": 0, "1": 0, "1.5": 0, "2.0": 0, "2.5": 0, "3.0": 0, "4.0": 0, "5.0": 0, "7.5": 0, "10.0": 0, "12.5": 0, "15.0": 0, "20.0": 0}, "VEHICULAR_TRAILER": {"0": 191, "0.1": 735, "0.5": 440, "1": 871, "1.5": 137, "2.0": 578, "2.5": 173, "3.0": 33, "4.0": 1368, "5.0": 80, "7.5": 1669, "10.0": 0, "12.5": 0, "15.0": 0, "20.0": 0}, "WHEELCHAIR": {"0": 0, "0.1": 0, "0.5": 0, "1": 0, "1.5": 0, "2.0": 0, "2.5": 0, "3.0": 0, "4.0": 0, "5.0": 0, "7.5": 0, "10.0": 0, "12.5": 0, "15.0": 0, "20.0": 0}, "WHEELED_DEVICE": {"0": 0, "0.1": 0, "0.5": 0, "1": 0, "1.5": 0, "2.0": 0, "2.5": 0, "3.0": 0, "4.0": 0, "5.0": 0, "7.5": 0, "10.0": 0, "12.5": 0, "15.0": 0, "20.0": 0}, "WHEELED_RIDER": {"0": 0, "0.1": 0, "0.5": 0, "1": 0, "1.5": 0, "2.0": 0, "2.5": 0, "3.0": 0, "4.0": 0, "5.0": 0, "7.5": 0, "10.0": 0, "12.5": 0, "15.0": 0, "20.0": 0}}